hi_seokxkyu/__init__.py
hi_seokxkyu/hello.py
hi_Seokxkyu-9.0.0.dist-info/METADATA
hi_Seokxkyu-9.0.0.dist-info/WHEEL
hi_Seokxkyu-9.0.0.dist-info/entry_points.txt
hi_Seokxkyu-9.0.0.dist-info/top_level.txt
hi_Seokxkyu-9.0.0.dist-info/RECORD
